awsecr/__init__.py
awsecr/awsecr.py
awsecr/cli.py
awsecr/exception.py
awsecr/image.py
awsecr/repository.py
awsecr-0.5.5.dist-info/LICENSE
awsecr-0.5.5.dist-info/METADATA
awsecr-0.5.5.dist-info/WHEEL
awsecr-0.5.5.dist-info/entry_points.txt
awsecr-0.5.5.dist-info/top_level.txt
awsecr-0.5.5.dist-info/RECORD
