Metadata-Version: 2.1
Name: awsecr
Version: 0.5.5
Summary: Easy interaction with AWS ECR from a CLI
Home-page: https://github.com/glasswalk3r/awsecr
Author: Alceu Rodrigues de Freitas Junior
Author-email: glasswalk3r@yahoo.com.br
Keywords: awsecr
Classifier: Development Status :: 4 - Beta
Classifier: Intended Audience :: Developers
Classifier: Natural Language :: English
Classifier: Programming Language :: Python :: 3
Classifier: Programming Language :: Python :: 3.8
Classifier: Programming Language :: Python :: 3.9
Classifier: Programming Language :: Python :: 3.10
Requires-Python: >=3.8
License-File: LICENSE
Requires-Dist: boto3==1.34.154
Requires-Dist: docker==7.1.0
Requires-Dist: terminaltables==3.1.10
Requires-Dist: colorama==0.4.6
Requires-Dist: boto3-stubs[ecr,sts]==1.34.155
